{"updated":1772562919,"stocks":{"SPY":{"p":680.56,"c":-5.82,"pct":-0.85},"QQQ":{"p":602.16,"c":-5.93,"pct":-0.98},"DIA":{"p":485.44,"c":-3.74,"pct":-0.76},"AAPL":{"p":261.65,"c":-3.06,"pct":-1.16},"MSFT":{"p":405.62,"c":7.08,"pct":1.78},"GOOGL":{"p":301.54,"c":-4.98,"pct":-1.62},"AMZN":{"p":207.94,"c":-0.45,"pct":-0.22},"NVDA":{"p":180.27,"c":-2.1,"pct":-1.15},"TSLA":{"p":393.27,"c":-10.05,"pct":-2.49},"META":{"p":656.06,"c":2.5,"pct":0.38},"JPM":{"p":301.63,"c":4.07,"pct":1.37},"V":{"p":320.55,"c":0.04,"pct":0.01},"BRK.B":{"p":482.36,"c":2.19,"pct":0.46},"UNH":{"p":288.6,"c":-6.33,"pct":-2.15},"JNJ":{"p":245.98,"c":-2.58,"pct":-1.04},"WMT":{"p":127.36,"c":0.27,"pct":0.21},"XOM":{"p":151.95,"c":-2.27,"pct":-1.47},"AMD":{"p":191.73,"c":-6.89,"pct":-3.47}},"metals":{"gold":{"p":5111.3,"c":-200.3,"pct":-3.77},"silver":{"p":83.61,"c":-5.25,"pct":-5.91},"platinum":{"p":2091.2,"c":-223.7,"pct":-9.66},"palladium":{"p":1678.5,"c":-116.4,"pct":-6.49}}}